neon_utterance_translator_plugin/__init__.py
neon_utterance_translator_plugin-0.2.1.dist-info/METADATA
neon_utterance_translator_plugin-0.2.1.dist-info/WHEEL
neon_utterance_translator_plugin-0.2.1.dist-info/entry_points.txt
neon_utterance_translator_plugin-0.2.1.dist-info/top_level.txt
neon_utterance_translator_plugin-0.2.1.dist-info/zip-safe
neon_utterance_translator_plugin-0.2.1.dist-info/RECORD
